package com.amazon.ws.emr.hadoop.fs.shaded.com.google.common.util.concurrent;

class SerializingExecutor$1
{
  SerializingExecutor$1(SerializingExecutor paramSerializingExecutor) {}
  
  /* Error */
  public String toString()
  {
    // Byte code:
    //   0: ldc 22
    //   2: aload_0
    //   3: invokespecial 24	java/lang/Object:toString	()Ljava/lang/String;
    //   6: invokestatic 30	java/lang/String:valueOf	(Ljava/lang/Object;)Ljava/lang/String;
    //   9: dup
    //   10: invokevirtual 34	java/lang/String:length	()I
    //   13: ifeq +9 -> 22
    //   16: invokevirtual 38	java/lang/String:concat	(Ljava/lang/String;)Ljava/lang/String;
    //   19: goto +12 -> 31
    //   22: pop
    //   23: new 26	java/lang/String
    //   26: dup_x1
    //   27: swap
    //   28: invokespecial 41	java/lang/String:<init>	(Ljava/lang/String;)V
    //   31: areturn
    // Line number table:
    //   Java source line #83	-> byte code offset #0
    // Local variable table:
    //   start	length	slot	name	signature
    //   0	32	0	this	1
  }
}

/* Location:
 * Qualified Name:     com.amazon.ws.emr.hadoop.fs.shaded.com.google.common.util.concurrent.SerializingExecutor.1
 * Java Class Version: 6 (50.0)
 * JD-Core Version:    0.7.1
 */